Products.MeetingLiege-4.2.16.4-py3.12-nspkg.pth
Products/MeetingLiege/README.txt
Products/MeetingLiege/__init__.py
Products/MeetingLiege/adapters.py
Products/MeetingLiege/config.py
Products/MeetingLiege/configure.zcml
Products/MeetingLiege/events.py
Products/MeetingLiege/events.zcml
Products/MeetingLiege/indexes.py
Products/MeetingLiege/interfaces.py
Products/MeetingLiege/overrides.py
Products/MeetingLiege/overrides.zcml
Products/MeetingLiege/profiles.zcml
Products/MeetingLiege/refresh.txt
Products/MeetingLiege/setuphandlers.py
Products/MeetingLiege/testing.py
Products/MeetingLiege/testing.zcml
Products/MeetingLiege/utils.py
Products/MeetingLiege/version.txt
Products/MeetingLiege/Extensions/__init__.py
Products/MeetingLiege/Extensions/utils.py
Products/MeetingLiege/browser/__init__.py
Products/MeetingLiege/browser/configure.zcml
Products/MeetingLiege/browser/overrides.py
Products/MeetingLiege/browser/views.py
Products/MeetingLiege/browser/overrides/images/details.png
Products/MeetingLiege/browser/overrides/images/more_infos.png
Products/MeetingLiege/browser/templates/item_main_infos.pt
Products/MeetingLiege/locales/PloneMeeting.pot
Products/MeetingLiege/locales/collective.eeafaceted.z3ctable.pot
Products/MeetingLiege/locales/datagridfield.pot
Products/MeetingLiege/locales/eea.pot
Products/MeetingLiege/locales/imio.actionspanel.pot
Products/MeetingLiege/locales/imio.history.pot
Products/MeetingLiege/locales/plone.pot
Products/MeetingLiege/locales/sync_pos.sh
Products/MeetingLiege/locales/en/LC_MESSAGES/PloneMeeting.po
Products/MeetingLiege/locales/en/LC_MESSAGES/collective.eeafaceted.z3ctable.po
Products/MeetingLiege/locales/en/LC_MESSAGES/datagridfield.po
Products/MeetingLiege/locales/en/LC_MESSAGES/eea.po
Products/MeetingLiege/locales/en/LC_MESSAGES/imio.actionspanel.po
Products/MeetingLiege/locales/en/LC_MESSAGES/imio.history.po
Products/MeetingLiege/locales/en/LC_MESSAGES/plone.po
Products/MeetingLiege/locales/fr/LC_MESSAGES/PloneMeeting.po
products_meetingliege-4.2.16.4.dist-info/METADATA
products_meetingliege-4.2.16.4.dist-info/WHEEL
products_meetingliege-4.2.16.4.dist-info/namespace_packages.txt
products_meetingliege-4.2.16.4.dist-info/top_level.txt
products_meetingliege-4.2.16.4.dist-info/RECORD
