Metadata-Version: 2.4
Name: Products.MeetingLiege
Version: 4.2.16.4
Summary: PloneMeeting profile for city of Liege
Home-page: http://www.imio.be/produits/gestion-des-deliberations
Author: Gauthier Bastien
Author-email: gauthier@imio.be
License: GPL
Keywords: plone official meetings management egov communesplone imio plonegov
Classifier: Development Status :: 6 - Mature
Classifier: Environment :: Web Environment
Classifier: Framework :: Plone
Classifier: Framework :: Plone :: 4.3
Classifier: License :: OSI Approved :: GNU General Public License (GPL)
Classifier: Operating System :: OS Independent
Classifier: Programming Language :: Python
Classifier: Programming Language :: Python :: 2.7
Classifier: Topic :: Office/Business
Requires-Dist: setuptools
Requires-Dist: appy
Requires-Dist: Products.CMFPlone
Requires-Dist: Pillow
Requires-Dist: Products.PloneMeeting
Provides-Extra: test
Requires-Dist: Products.PloneMeeting[test]; extra == "test"
Provides-Extra: templates
Requires-Dist: Genshi; extra == "templates"
Dynamic: author
Dynamic: author-email
Dynamic: classifier
Dynamic: description
Dynamic: home-page
Dynamic: keywords
Dynamic: license
Dynamic: provides-extra
Dynamic: requires-dist
Dynamic: summary
